asyncwhois/__init__.py
asyncwhois/client.py
asyncwhois/errors.py
asyncwhois/parse.py
asyncwhois/parse_rir.py
asyncwhois/parse_tld.py
asyncwhois/query.py
asyncwhois/tldparsers.py
asyncwhois/servers/__init__.py
asyncwhois/servers/domains.py
asyncwhois/servers/ipv4.py
asyncwhois-1.1.9.dist-info/METADATA
asyncwhois-1.1.9.dist-info/WHEEL
asyncwhois-1.1.9.dist-info/licenses/LICENSE
asyncwhois-1.1.9.dist-info/RECORD
