Metadata-Version: 2.3
Name: asyncwhois
Version: 1.1.9
Summary: Python WHOIS and RDAP utility for querying and parsing information about Domains, IPv4s, IPv6s, and AS numbers.
Project-URL: Homepage, https://github.com/pogzyb/asyncwhois
Project-URL: Issues, https://github.com/pogzyb/asyncwhois/issues
Author-email: Joe Obarzanek <pogzyb@umich.edu>
License: MIT License
License-File: LICENSE
Classifier: Environment :: Web Environment
Classifier: Framework :: AsyncIO
Classifier: Intended Audience :: Developers
Classifier: License :: OSI Approved :: MIT License
Classifier: Operating System :: OS Independent
Classifier: Programming Language :: Python :: 3 :: Only
Classifier: Topic :: Internet :: WWW/HTTP
Classifier: Topic :: Security
Classifier: Topic :: Software Development
Requires-Python: >=3.9
Requires-Dist: python-dateutil>=2.9.0
Requires-Dist: python-socks[asyncio]>=2.0.2
Requires-Dist: tldextract>=3.2.0
Requires-Dist: whodap>=0.1.12
